[
	{
		"name": "Disha Katia",
		"phone": "7009568159",
		"email": "dishakatia@gmail.com",
		"hall": "SNVH-IGH B209",
		"mess": "",
		"isAdmin": false,
		"otp": null,
		"instituteID": "IITD",
		"gender": "F"
	},
	{
		"name": "Shriya",
		"phone": "9958645401",
		"email": "shriya.khare1311@gmail.com",
		"hall": "SNVH-IGH B209",
		"mess": "",
		"isAdmin": false,
		"otp": null,
		"instituteID": "IITD",
		"gender": "F"
	},
	{
		"name": "Sukriti",
		"phone": "7895387605",
		"email": "sukritikhatri22@gmail.com",
		"hall": "SNVH-IGH B209",
		"mess": "",
		"isAdmin": false,
		"otp": null,
		"instituteID": "IITD",
		"gender": "F"
	},
	{
		"name": "Afreen Haider",
		"phone": "9123326525",
		"email": "afreenhaider07@gmail.com",
		"hall": "SNVH-IGH B210",
		"mess": "",
		"isAdmin": false,
		"otp": null,
		"instituteID": "IITD",
		"gender": "F"
	},
	{
		"name": "Maathangi Anirudh",
		"phone": "7827736356",
		"email": "maathangi.a@gmail.com",
		"hall": "SNVH-IGH B210",
		"mess": "",
		"isAdmin": false,
		"otp": null,
		"instituteID": "IITD",
		"gender": "F"
	},
	{
		"name": "Aarushi Mittal",
		"phone": "9958025601",
		"email": "aarushimittal08@gmail.com",
		"hall": "SNVH-IGH B210",
		"mess": "",
		"isAdmin": false,
		"otp": null,
		"instituteID": "IITD",
		"gender": "F"
	},
	{
		"name": "Shivaani Hari",
		"phone": "9205959258",
		"email": "shivaani.hari2550@gmail.com",
		"hall": "SNVH-IGH B210",
		"mess": "",
		"isAdmin": false,
		"otp": null,
		"instituteID": "IITD",
		"gender": "F"
	},
	{
		"name": "Aahna Jain",
		"phone": "8950139605",
		"email": "aahnajain1@gmail.com",
		"hall": "SNVH-IGH B210",
		"mess": "",
		"isAdmin": false,
		"otp": null,
		"instituteID": "IITD",
		"gender": "F"
	},
	{
		"name": "Sara",
		"phone": "7678683689",
		"email": "sarasinha2001@gmail.com",
		"hall": "SNVH-IGH B211",
		"mess": "",
		"isAdmin": false,
		"otp": null,
		"instituteID": "IITD",
		"gender": "F"
	},
	{
		"name": "M Bhavya",
		"phone": "7837801846",
		"email": "mbhavya2003@gmail.com",
		"hall": "SNVH-IGH B211",
		"mess": "",
		"isAdmin": false,
		"otp": null,
		"instituteID": "IITD",
		"gender": "F"
	},
	{
		"name": "Swarnima Sameeksha",
		"phone": "9155168066",
		"email": "swarnima662@gmail.com",
		"hall": "SNVH-IGH B211",
		"mess": "",
		"isAdmin": false,
		"otp": null,
		"instituteID": "IITD",
		"gender": "F"
	},
	{
		"name": "Srishti",
		"phone": "8813925666",
		"email": "srishtichayal11@gmail.com",
		"hall": "SNVH-IGH B211",
		"mess": "",
		"isAdmin": false,
		"otp": null,
		"instituteID": "IITD",
		"gender": "F"
	},
	{
		"name": "Mitali Nanda",
		"phone": "9818020966",
		"email": "nmitalinanda@gmail.com",
		"hall": "SNVH-IGH B211",
		"mess": "",
		"isAdmin": false,
		"otp": null,
		"instituteID": "IITD",
		"gender": "F"
	},
	{
		"name": "Shreshtha Goel",
		"phone": "8527355140",
		"email": "shreshthagoel25@gmail.com",
		"hall": "SNVH-IGH B212",
		"mess": "",
		"isAdmin": false,
		"otp": null,
		"instituteID": "IITD",
		"gender": "F"
	},
	{
		"name": "Deshna",
		"phone": "9852400007",
		"email": "deshnamehmi@gmail.com",
		"hall": "SNVH-IGH B212",
		"mess": "",
		"isAdmin": false,
		"otp": null,
		"instituteID": "IITD",
		"gender": "F"
	},
	{
		"name": "Shreya Gupta",
		"phone": "8109705093",
		"email": "shreyagupta0605@gmail.com",
		"hall": "SNVH-IGH B212",
		"mess": "",
		"isAdmin": false,
		"otp": null,
		"instituteID": "IITD",
		"gender": "F"
	},
	{
		"name": "Aditi Singh",
		"phone": "7892304573",
		"email": "aditisingh23.1504@gmail.com",
		"hall": "SNVH-IGH B212",
		"mess": "",
		"isAdmin": false,
		"otp": null,
		"instituteID": "IITD",
		"gender": "F"
	},
	{
		"name": "Chandni",
		"phone": "9408636630",
		"email": "chandni2963@gmail.com",
		"hall": "SNVH-IGH B212",
		"mess": "",
		"isAdmin": false,
		"otp": null,
		"instituteID": "IITD",
		"gender": "F"
	},
	{
		"name": "Sanya Dutt",
		"phone": "7985085285",
		"email": "ph1200728@iitd.ac.in",
		"hall": "SNVH-IGH B213",
		"mess": "",
		"isAdmin": false,
		"otp": null,
		"instituteID": "IITD",
		"gender": "F"
	},
	{
		"name": "Samiksha Sagar",
		"phone": "9027252529",
		"email": "ee1200545@iitd.ac.in",
		"hall": "SNVH-IGH B213",
		"mess": "",
		"isAdmin": false,
		"otp": null,
		"instituteID": "IITD",
		"gender": "F"
	},
	{
		"name": "Tripti Jain",
		"phone": "9877799216",
		"email": "tripti16j@gmail.com",
		"hall": "SNVH-IGH B213",
		"mess": "",
		"isAdmin": false,
		"otp": null,
		"instituteID": "IITD",
		"gender": "F"
	},
	{
		"name": "Khushboo Choudhary",
		"phone": "9549690621",
		"email": "me1200942@iitd.ac.in",
		"hall": "SNVH-IGH B213",
		"mess": "",
		"isAdmin": false,
		"otp": null,
		"instituteID": "IITD",
		"gender": "F"
	},
	{
		"name": "Tanushree Pandey",
		"phone": "9450743828",
		"email": "me1200979@iitd.ac.in",
		"hall": "SNVH-IGH B213",
		"mess": "",
		"isAdmin": false,
		"otp": null,
		"instituteID": "IITD",
		"gender": "F"
	},
	{
		"name": "Vidhi Sharma",
		"phone": "8827122363",
		"email": "vidhi.iitdelhi@gmail.com",
		"hall": "SNVH-IGH B301",
		"mess": "",
		"isAdmin": false,
		"otp": null,
		"instituteID": "IITD",
		"gender": "F"
	},
	{
		"name": "Meenakshi Mina",
		"phone": "8824390516",
		"email": "meenakshi.meena2712@gmail.com",
		"hall": "SNVH-IGH B301",
		"mess": "",
		"isAdmin": false,
		"otp": null,
		"instituteID": "IITD",
		"gender": "F"
	},
	{
		"name": "Divyanshi Naresh",
		"phone": "8905043823",
		"email": "ch1210429@iitd.ac.in",
		"hall": "SNVH-IGH B301",
		"mess": "",
		"isAdmin": false,
		"otp": null,
		"instituteID": "IITD",
		"gender": "F"
	},
	{
		"name": "Mandira Das",
		"phone": "8250615233",
		"email": "ch7210467@iitd.ac.in",
		"hall": "SNVH-IGH B301",
		"mess": "",
		"isAdmin": false,
		"otp": null,
		"instituteID": "IITD",
		"gender": "F"
	},
	{
		"name": "Aanya Khurana",
		"phone": "9818198988",
		"email": "cs1210084@iitd.ac.in",
		"hall": "SNVH-IGH B301",
		"mess": "",
		"isAdmin": false,
		"otp": null,
		"instituteID": "IITD",
		"gender": "F"
	},
	{
		"name": "Dipshika Deepak Karmalkar",
		"phone": "9168432246",
		"email": "Dipshikakarmalkar50@gmail.com",
		"hall": "SNVH-IGH B302",
		"mess": "",
		"isAdmin": false,
		"otp": null,
		"instituteID": "IITD",
		"gender": "F"
	},
	{
		"name": "Riya",
		"phone": "7903215878",
		"email": "bb1221011@dbeb.iitd.ac.in",
		"hall": "SNVH-IGH B302",
		"mess": "",
		"isAdmin": false,
		"otp": null,
		"instituteID": "IITD",
		"gender": "F"
	},
	{
		"name": "Nidhi Pandey",
		"phone": "6388665322",
		"email": "bb1221393@dbeb.iitd.ac.in",
		"hall": "SNVH-IGH B302",
		"mess": "",
		"isAdmin": false,
		"otp": null,
		"instituteID": "IITD",
		"gender": "F"
	},
	{
		"name": "Kumari Ritika",
		"phone": "8929880157",
		"email": "ce1221048@iitd.ac.in",
		"hall": "SNVH-IGH B302",
		"mess": "",
		"isAdmin": false,
		"otp": null,
		"instituteID": "IITD",
		"gender": "F"
	},
	{
		"name": "Sukriti Singh",
		"phone": "6394276867",
		"email": "ce1221549@iitd.ac.in",
		"hall": "SNVH-IGH B302",
		"mess": "",
		"isAdmin": false,
		"otp": null,
		"instituteID": "IITD",
		"gender": "F"
	},
	{
		"name": "Aditi Narayan Lal",
		"phone": "9529907193",
		"email": "aditinlal2005@gmail.com",
		"hall": "SNVH-IGH B303",
		"mess": "",
		"isAdmin": false,
		"otp": null,
		"instituteID": "IITD",
		"gender": "F"
	},
	{
		"name": "Ananyaa Agrawal",
		"phone": "8817648565",
		"email": "ananyaa1123@gmail.com",
		"hall": "SNVH-IGH B303",
		"mess": "",
		"isAdmin": false,
		"otp": null,
		"instituteID": "IITD",
		"gender": "F"
	},
	{
		"name": "Riti Verma",
		"phone": "9958079981",
		"email": "cs5221644@iitd.ac.in",
		"hall": "SNVH-IGH B303",
		"mess": "",
		"isAdmin": false,
		"otp": null,
		"instituteID": "IITD",
		"gender": "F"
	},
	{
		"name": "Ananya",
		"phone": "9368919904",
		"email": "ananyaspta@gmail.com",
		"hall": "SNVH-IGH B303",
		"mess": "",
		"isAdmin": false,
		"otp": null,
		"instituteID": "IITD",
		"gender": "F"
	},
	{
		"name": "Payel Halder",
		"phone": "7439081603",
		"email": "hpayel98@gmail.com",
		"hall": "SNVH-IGH B303",
		"mess": "",
		"isAdmin": false,
		"otp": null,
		"instituteID": "IITD",
		"gender": "F"
	},
	{
		"name": "Tanvi Bansal",
		"phone": "7526970192",
		"email": "bansal.tanvi2911@gmail.com",
		"hall": "SNVH-IGH B304",
		"mess": "",
		"isAdmin": false,
		"otp": null,
		"instituteID": "IITD",
		"gender": "F"
	},
	{
		"name": "Aditi Agrawal",
		"phone": "7000146018",
		"email": "tt1211164@iitd.ac.in",
		"hall": "SNVH-IGH B304",
		"mess": "",
		"isAdmin": false,
		"otp": null,
		"instituteID": "IITD",
		"gender": "F"
	},
	{
		"name": "Nandini Sandeep",
		"phone": "9035001287",
		"email": "nandininithyasandeep@gmail.com",
		"hall": "SNVH-IGH B304",
		"mess": "",
		"isAdmin": false,
		"otp": null,
		"instituteID": "IITD",
		"gender": "F"
	},
	{
		"name": "Aadya Shree",
		"phone": "7070879099",
		"email": "aadyashree001@gmail.com",
		"hall": "SNVH-IGH B304",
		"mess": "",
		"isAdmin": false,
		"otp": null,
		"instituteID": "IITD",
		"gender": "F"
	},
	{
		"name": "Manisha Vaishy",
		"phone": "7898784811",
		"email": "vaishy.manisha3010@gmail.com",
		"hall": "SNVH-IGH B304",
		"mess": "",
		"isAdmin": false,
		"otp": null,
		"instituteID": "IITD",
		"gender": "F"
	},
	{
		"name": "Vidushi",
		"phone": "6280175938",
		"email": "vidushi2525@gmail.com",
		"hall": "SNVH-IGH B305",
		"mess": "",
		"isAdmin": false,
		"otp": null,
		"instituteID": "IITD",
		"gender": "F"
	},
	{
		"name": "Devanshi Malik",
		"phone": "8949729455",
		"email": "devanshimalik11@gmail.com",
		"hall": "SNVH-IGH B305",
		"mess": "",
		"isAdmin": false,
		"otp": null,
		"instituteID": "IITD",
		"gender": "F"
	},
	{
		"name": "Nidhi Saini",
		"phone": "9588026618",
		"email": "nidhisaini1203@gmail.com",
		"hall": "SNVH-IGH B305",
		"mess": "",
		"isAdmin": false,
		"otp": null,
		"instituteID": "IITD",
		"gender": "F"
	},
	{
		"name": "Umangh Nagal",
		"phone": "7988620856",
		"email": "nagalumangh@gmail.com",
		"hall": "SNVH-IGH B305",
		"mess": "",
		"isAdmin": false,
		"otp": null,
		"instituteID": "IITD",
		"gender": "F"
	},
	{
		"name": "Anushka Meena",
		"phone": "9667178566",
		"email": "anushkam251@gmail.com",
		"hall": "SNVH-IGH B305",
		"mess": "",
		"isAdmin": false,
		"otp": null,
		"instituteID": "IITD",
		"gender": "F"
	},
	{
		"name": "Ankita",
		"phone": "7974598455",
		"email": "choureanky@gmail.com",
		"hall": "SNVH-IGH B306",
		"mess": "",
		"isAdmin": false,
		"otp": null,
		"instituteID": "IITD",
		"gender": "F"
	},
	{
		"name": "Yamini",
		"phone": "8788656593",
		"email": "yaminikhajekar@gmail.com",
		"hall": "SNVH-IGH B306",
		"mess": "",
		"isAdmin": false,
		"otp": null,
		"instituteID": "IITD",
		"gender": "F"
	},
	{
		"name": "Shreya Gupta",
		"phone": "9582098771",
		"email": "shreya.gupta19@gmail.com",
		"hall": "SNVH-IGH B306",
		"mess": "",
		"isAdmin": false,
		"otp": null,
		"instituteID": "IITD",
		"gender": "F"
	},
	{
		"name": "Ambika Batra",
		"phone": "9760270362",
		"email": "bb1210329@iitd.ac.in",
		"hall": "SNVH-IGH B306",
		"mess": "",
		"isAdmin": false,
		"otp": null,
		"instituteID": "IITD",
		"gender": "F"
	},
	{
		"name": "Kashish Kapadia",
		"phone": "8987100488",
		"email": "kashishkapadia8757@gmail.com",
		"hall": "SNVH-IGH B306",
		"mess": "",
		"isAdmin": false,
		"otp": null,
		"instituteID": "IITD",
		"gender": "F"
	},
	{
		"name": "Ananya Damesha",
		"phone": "8989465246",
		"email": "dameshaananya@gmail.com",
		"hall": "SNVH-IGH B307",
		"mess": "",
		"isAdmin": false,
		"otp": null,
		"instituteID": "IITD",
		"gender": "F"
	},
	{
		"name": "Vidyadarshini",
		"phone": "9003380881",
		"email": "rvidyadarshini@gmail.com",
		"hall": "SNVH-IGH B307",
		"mess": "",
		"isAdmin": false,
		"otp": null,
		"instituteID": "IITD",
		"gender": "F"
	},
	{
		"name": "Naina Jain",
		"phone": "8486369691",
		"email": "naina05112003@gmail.com",
		"hall": "SNVH-IGH B307",
		"mess": "",
		"isAdmin": false,
		"otp": null,
		"instituteID": "IITD",
		"gender": "F"
	},
	{
		"name": "Sanskriti Dangi",
		"phone": "9431769149",
		"email": "sanskritidangi07@gmail.com",
		"hall": "SNVH-IGH B307",
		"mess": "",
		"isAdmin": false,
		"otp": null,
		"instituteID": "IITD",
		"gender": "F"
	}
]
